LICENSE
MANIFEST.in
README.md
requirements.txt
setup.py
predictionball/__init__.py
predictionball/args.py
predictionball/cluster.py
predictionball/cluster_model.py
predictionball/kalshi.py
predictionball/outcome_model.py
predictionball/polymarket.py
predictionball/prediction_market_model.py
predictionball/predictit.py
predictionball/pull.py
predictionball.egg-info/PKG-INFO
predictionball.egg-info/SOURCES.txt
predictionball.egg-info/dependency_links.txt
predictionball.egg-info/not-zip-safe
predictionball.egg-info/requires.txt
predictionball.egg-info/top_level.txt
tests/__init__.py