Metadata-Version: 2.1
Name: predictionball
Version: 0.0.1
Summary: A library for pulling in and normalising prediction market data.
Home-page: https://github.com/8W9aG/predictionball
Author: Will Sackfield
Author-email: will.sackfield@gmail.com
License: MIT
Keywords: prediction markets
Classifier: License :: OSI Approved :: MIT License
Classifier: Programming Language :: Python :: 3
License-File: LICENSE
Requires-Dist: pandas>=2.2.3
Requires-Dist: py-clob-client>=0.20.0
Requires-Dist: python-dotenv>=1.1.0
Requires-Dist: pydantic>=2.11.5
Requires-Dist: requests>=2.32.3
Requires-Dist: pyarrow>=20.0.0
Requires-Dist: sentence_transformers>=4.1.0
Requires-Dist: scikit-learn>=1.6.1
